<annotation>
	<folder>basketball_1</folder>
	<filename>basketball_129.png</filename>
	<path>/Users/yagmur/Desktop/datasets/basketball_1/basketball_129.png</path>
	<source>
		<database>Unknown</database>
	</source>
	<size>
		<width>700</width>
		<height>394</height>
		<depth>3</depth>
	</size>
	<segmented>0</segmented>
	<object>
		<name>player</name>
		<pose>Unspecified</pose>
		<truncated>1</truncated>
		<difficult>0</difficult>
		<bndbox>
			<xmin>80</xmin>
			<ymin>46</ymin>
			<xmax>375</xmax>
			<ymax>394</ymax>
		</bndbox>
	</object>
	<object>
		<name>player</name>
		<pose>Unspecified</pose>
		<truncated>1</truncated>
		<difficult>0</difficult>
		<bndbox>
			<xmin>393</xmin>
			<ymin>185</ymin>
			<xmax>653</xmax>
			<ymax>394</ymax>
		</bndbox>
	</object>
</annotation>
